ruquests-1.0.0.dist-info/METADATA
ruquests-1.0.0.dist-info/WHEEL
ruquests-1.0.0.dist-info/license_files/LICENSE
ruquests.libs/libssl-91d34894.so.3
ruquests.libs/libcrypto-a50d99cb.so.3
ruquests/__init__.pyi
ruquests/py.typed
ruquests/__init__.py
ruquests/bindings.cpython-312-x86_64-linux-gnu.so
ruquests-1.0.0.dist-info/RECORD
