Metadata-Version: 2.3
Name: ruquests
Version: 1.0.0
Requires-Dist: patchelf >=0.17.2.1
License-File: LICENSE
Summary: Add your description here
Author-email: João Severo <joaovbsevero@gmail.com>
Requires-Python: >=3.12
